{"cameraMode":{"drawMode":0,"name":"Shaded","section":"Shading Mode"},"sceneLighting":true,"audioPlay":false,"sceneViewState":{"m_AlwaysRefresh":false,"showFog":true,"showSkybox":true,"showFlares":true,"showImageEffects":true,"showParticleSystems":true,"showVisualEffectGraphs":true,"m_FxEnabled":true},"in2DMode":false,"pivot":{"x":-46.18898010253906,"y":1.3786067962646485,"z":109.49171447753906},"rotation":{"x":-0.08973909169435501,"y":0.231456458568573,"z":-0.0214491356164217,"w":-0.9684671759605408},"size":86.3316879272461,"orthographic":false}